Metadata-Version: 1.1
Name: vijayCal0204
Version: 0.0.1
Summary: A very basic calculator
Home-page: UNKNOWN
Author: Vijay Kanniah
Author-email: x21188955@student.ncirl.ie
License: MIT
Keywords: calculator
Platform: UNKNOWN
Classifier: Development Status :: 5 - Production/Stable
Classifier: Intended Audience :: Education
Classifier: Operating System :: Microsoft :: Windows :: Windows 10
Classifier: License :: OSI Approved :: MIT License
Classifier: Programming Language :: Python :: 3
